iduredis/__init__.py
iduredis/_version.py
iduredis/lock_manager.py
iduredis/redis_manager.py
idu_redis_client-1.0.0.dist-info/METADATA
idu_redis_client-1.0.0.dist-info/WHEEL
idu_redis_client-1.0.0.dist-info/RECORD
