Metadata-Version: 2.1
Name: IDU-redis-client
Version: 1.0.0
Summary: --/--
License: BSD-3-Clause
Author: soldey
Author-email: 71354808+soldey@users.noreply.github.com
Requires-Python: >=3.10,<3.12
Classifier: License :: OSI Approved :: BSD License
Classifier: Programming Language :: Python :: 3
Classifier: Programming Language :: Python :: 3.10
Classifier: Programming Language :: Python :: 3.11
Requires-Dist: aioredlock (==0.7.3)
Requires-Dist: idu-config (>=1.0.0,<2.0.0)
Requires-Dist: loguru (>=0.7.2,<0.8.0)
Requires-Dist: redis (>=5.1.1,<6.0.0)
